LICENSE
README.md
setup.cfg
setup.py
pyupfile/__init__.py
pyupfile/__main__.py
pyupfile.egg-info/PKG-INFO
pyupfile.egg-info/SOURCES.txt
pyupfile.egg-info/dependency_links.txt
pyupfile.egg-info/entry_points.txt
pyupfile.egg-info/requires.txt
pyupfile.egg-info/top_level.txt