Metadata-Version: 2.1
Name: pyupfile
Version: 1.0.1
Summary: pyupfile allows you to upload any file to https://file.io site using their API
Home-page: https://github.com/hemish04082005/pyupfile/
Author: Hemish
Author-email: hemish04082005@gmail.com
License: MIT
Download-URL: https://github.com/hemish04082005/pyupfile/archive/1.0.1.tar.gz
Project-URL: Bug Tracker, https://github.com/hemish04082005/pyupfile/issues
Keywords: python,uploader,upload,file,python3
Platform: any
Classifier: Programming Language :: Python :: 3
Classifier: License :: OSI Approved :: MIT License
Classifier: Operating System :: OS Independent
Requires-Python: >=3.4
